acdc_aws_etl_pipeline/__init__.py
acdc_aws_etl_pipeline/ingest/ingest.py
acdc_aws_etl_pipeline/upload/__init__.py
acdc_aws_etl_pipeline/upload/gen3datasubmitter.py
acdc_aws_etl_pipeline/upload/metadata_deleter.py
acdc_aws_etl_pipeline/upload/metadata_submitter.py
acdc_aws_etl_pipeline/upload/upload_synthdata_s3.py
acdc_aws_etl_pipeline/utils/athena_utils.py
acdc_aws_etl_pipeline/utils/dbt_utils.py
acdc_aws_etl_pipeline/utils/release_writer.py
acdc_aws_etl_pipeline/validate/validate.py
acdc_aws_etl_pipeline-0.7.6.dist-info/METADATA
acdc_aws_etl_pipeline-0.7.6.dist-info/WHEEL
acdc_aws_etl_pipeline-0.7.6.dist-info/RECORD
