Metadata-Version: 2.4
Name: acdc_aws_etl_pipeline
Version: 0.7.6
Summary: Tools for ACDC ETL pipeline
Author: JoshuaHarris391
Author-email: harjo391@gmail.com
Requires-Python: >=3.9.5,<4.0.0
Classifier: Programming Language :: Python :: 3
Classifier: Programming Language :: Python :: 3.10
Classifier: Programming Language :: Python :: 3.11
Classifier: Programming Language :: Python :: 3.12
Classifier: Programming Language :: Python :: 3.13
Classifier: Programming Language :: Python :: 3.14
Requires-Dist: boto3
Requires-Dist: dbt-athena (==1.9.4)
Requires-Dist: dbt-core (==1.9.4)
Requires-Dist: gen3 (>=4.27.4,<5.0.0)
Requires-Dist: gen3_validator (>=2.0.0,<3.0.0)
Requires-Dist: numpy (<2.0.0)
Requires-Dist: pyjwt (>=2.10.1,<3.0.0)
Requires-Dist: pytest
Requires-Dist: python-dotenv
Requires-Dist: pytz (>=2025.2,<2026.0)
Requires-Dist: pyyaml (>=6.0.2,<7.0.0)
Requires-Dist: s3fs (==2025.10.0)
Requires-Dist: tenacity (>=8.2,<10.0)
Requires-Dist: tzlocal (>=5.3.1,<6.0.0)
